{
"meta":{"test_sets":[],"test_metrics":[],"learn_metrics":[{"best_value":"Min","name":"MultiClass"}],"launch_mode":"Train","parameters":"","iteration_count":300,"learn_sets":["learn"],"name":"experiment"},
"iterations":[
{"learn":[1.445692946],"iteration":0,"passed_time":0.6556909613,"remaining_time":196.0515974},
{"learn":[1.241496373],"iteration":1,"passed_time":1.080746232,"remaining_time":161.0311886},
{"learn":[1.095057242],"iteration":2,"passed_time":1.555958169,"remaining_time":154.0398587},
{"learn":[0.9834514843],"iteration":3,"passed_time":2.063173467,"remaining_time":152.6748366},
{"learn":[0.896861749],"iteration":4,"passed_time":2.536443442,"remaining_time":149.6501631},
{"learn":[0.8270971519],"iteration":5,"passed_time":2.99132141,"remaining_time":146.5747491},
{"learn":[0.7660649315],"iteration":6,"passed_time":3.399582724,"remaining_time":142.2968197},
{"learn":[0.7143910969],"iteration":7,"passed_time":4.007103146,"remaining_time":146.2592648},
{"learn":[0.6710231556],"iteration":8,"passed_time":4.541593358,"remaining_time":146.8448519},
{"learn":[0.633919124],"iteration":9,"passed_time":4.976076149,"remaining_time":144.3062083},
{"learn":[0.6007741536],"iteration":10,"passed_time":5.38432488,"remaining_time":141.4608991},
{"learn":[0.5725679692],"iteration":11,"passed_time":5.793490384,"remaining_time":139.0437692},
{"learn":[0.5470583318],"iteration":12,"passed_time":6.222472618,"remaining_time":137.3730493},
{"learn":[0.5236701842],"iteration":13,"passed_time":6.610673916,"remaining_time":135.0466243},
{"learn":[0.5030561413],"iteration":14,"passed_time":6.980904738,"remaining_time":132.63719},
{"learn":[0.4847496186],"iteration":15,"passed_time":7.413530025,"remaining_time":131.5901579},
{"learn":[0.4685154606],"iteration":16,"passed_time":7.879299775,"remaining_time":131.1671668},
{"learn":[0.4537707789],"iteration":17,"passed_time":8.251118649,"remaining_time":129.2675255},
{"learn":[0.4392615675],"iteration":18,"passed_time":8.668663403,"remaining_time":128.2049693},
{"learn":[0.4269891707],"iteration":19,"passed_time":9.086008202,"remaining_time":127.2041148},
{"learn":[0.415967025],"iteration":20,"passed_time":9.490355344,"remaining_time":126.0861496},
{"learn":[0.4050064047],"iteration":21,"passed_time":9.899907216,"remaining_time":125.0988275},
{"learn":[0.3953268092],"iteration":22,"passed_time":10.38687029,"remaining_time":125.0940466},
{"learn":[0.3863645068],"iteration":23,"passed_time":10.81592253,"remaining_time":124.383109},
{"learn":[0.3785074051],"iteration":24,"passed_time":11.25313697,"remaining_time":123.7845067},
{"learn":[0.3714653963],"iteration":25,"passed_time":11.63697477,"remaining_time":122.6358111},
{"learn":[0.3659388439],"iteration":26,"passed_time":11.99460068,"remaining_time":121.2787402},
{"learn":[0.3601407363],"iteration":27,"passed_time":12.35340202,"remaining_time":120.0044768},
{"learn":[0.3550110348],"iteration":28,"passed_time":12.87893645,"remaining_time":120.3514407},
{"learn":[0.3495394762],"iteration":29,"passed_time":13.28669357,"remaining_time":119.5802421},
{"learn":[0.3449731619],"iteration":30,"passed_time":13.8342129,"remaining_time":120.0452668},
{"learn":[0.3413265506],"iteration":31,"passed_time":14.23789159,"remaining_time":119.2423421},
{"learn":[0.3379542421],"iteration":32,"passed_time":14.64363313,"remaining_time":118.4803044},
{"learn":[0.3344769341],"iteration":33,"passed_time":14.96312896,"remaining_time":117.0644795},
{"learn":[0.3309665964],"iteration":34,"passed_time":15.35207912,"remaining_time":116.2371705},
{"learn":[0.3264030725],"iteration":35,"passed_time":15.86501455,"remaining_time":116.34344},
{"learn":[0.3234449244],"iteration":36,"passed_time":16.32360611,"remaining_time":116.029957},
{"learn":[0.3205808343],"iteration":37,"passed_time":16.81462369,"remaining_time":115.9324055},
{"learn":[0.3182436924],"iteration":38,"passed_time":17.16735295,"remaining_time":114.8892082},
{"learn":[0.3145043539],"iteration":39,"passed_time":17.61953022,"remaining_time":114.5269464},
{"learn":[0.312675577],"iteration":40,"passed_time":18.03195528,"remaining_time":113.9091809},
{"learn":[0.3099313017],"iteration":41,"passed_time":18.37591513,"remaining_time":112.8806215},
{"learn":[0.3081284256],"iteration":42,"passed_time":18.81669988,"remaining_time":112.4626016},
{"learn":[0.3050189239],"iteration":43,"passed_time":19.52571644,"remaining_time":113.6041684},
{"learn":[0.3016451841],"iteration":44,"passed_time":19.97075202,"remaining_time":113.1675948},
{"learn":[0.2993896677],"iteration":45,"passed_time":20.59855529,"remaining_time":113.7398488},
{"learn":[0.2965695536],"iteration":46,"passed_time":20.96974234,"remaining_time":112.8796769},
{"learn":[0.2952693742],"iteration":47,"passed_time":21.50979224,"remaining_time":112.9264092},
{"learn":[0.2928844615],"iteration":48,"passed_time":21.88917308,"remaining_time":112.1261723},
{"learn":[0.2914826765],"iteration":49,"passed_time":22.19469749,"remaining_time":110.9734874},
{"learn":[0.2900889054],"iteration":50,"passed_time":22.68321479,"remaining_time":110.7474604},
{"learn":[0.2879655355],"iteration":51,"passed_time":23.05343794,"remaining_time":109.9471656},
{"learn":[0.2859521262],"iteration":52,"passed_time":23.51596126,"remaining_time":109.5932534},
{"learn":[0.2847723299],"iteration":53,"passed_time":23.74118706,"remaining_time":108.1542966},
{"learn":[0.282831554],"iteration":54,"passed_time":24.09260359,"remaining_time":107.3215978},
{"learn":[0.2816529006],"iteration":55,"passed_time":24.34480606,"remaining_time":106.0737978},
{"learn":[0.2784695204],"iteration":56,"passed_time":24.715295,"remaining_time":105.365205},
{"learn":[0.2772324664],"iteration":57,"passed_time":25.10779067,"remaining_time":104.7600921},
{"learn":[0.2758758375],"iteration":58,"passed_time":25.48562405,"remaining_time":104.1022948},
{"learn":[0.2731202937],"iteration":59,"passed_time":25.78073712,"remaining_time":103.1229485},
{"learn":[0.2723597062],"iteration":60,"passed_time":26.19440595,"remaining_time":102.6305413},
{"learn":[0.2705434882],"iteration":61,"passed_time":26.64181644,"remaining_time":102.2701986},
{"learn":[0.2696475761],"iteration":62,"passed_time":26.98969442,"remaining_time":101.53266},
{"learn":[0.2686094542],"iteration":63,"passed_time":27.31384887,"remaining_time":100.7198177},
{"learn":[0.2676753106],"iteration":64,"passed_time":27.62613205,"remaining_time":99.87909281},
{"learn":[0.267028193],"iteration":65,"passed_time":27.9416848,"remaining_time":99.06597339},
{"learn":[0.2657063709],"iteration":66,"passed_time":28.25078593,"remaining_time":98.24527046},
{"learn":[0.2641091161],"iteration":67,"passed_time":28.63693877,"remaining_time":97.70249696},
{"learn":[0.2629994544],"iteration":68,"passed_time":28.96581029,"remaining_time":96.97249531},
{"learn":[0.2623270674],"iteration":69,"passed_time":29.21565389,"remaining_time":95.99429134},
{"learn":[0.2607583314],"iteration":70,"passed_time":29.58009995,"remaining_time":95.40623787},
{"learn":[0.259651779],"iteration":71,"passed_time":29.91436274,"remaining_time":94.72881534},
{"learn":[0.2581668842],"iteration":72,"passed_time":30.24802392,"remaining_time":94.05892369},
{"learn":[0.2573341736],"iteration":73,"passed_time":30.59105503,"remaining_time":93.42673564},
{"learn":[0.2567406131],"iteration":74,"passed_time":30.83083279,"remaining_time":92.49249837},
{"learn":[0.2557087817],"iteration":75,"passed_time":31.13965296,"remaining_time":91.78002979},
{"learn":[0.2551267967],"iteration":76,"passed_time":31.41637349,"remaining_time":90.98508165},
{"learn":[0.2539452514],"iteration":77,"passed_time":31.80711648,"remaining_time":90.52794691},
{"learn":[0.2532094681],"iteration":78,"passed_time":32.08233628,"remaining_time":89.74932049},
{"learn":[0.2524404074],"iteration":79,"passed_time":32.46652987,"remaining_time":89.28295714},
{"learn":[0.2517990191],"iteration":80,"passed_time":32.85528307,"remaining_time":88.83095053},
{"learn":[0.2509201321],"iteration":81,"passed_time":33.18506158,"remaining_time":88.22370029},
{"learn":[0.2504336692],"iteration":82,"passed_time":33.53165658,"remaining_time":87.66710214},
{"learn":[0.249707383],"iteration":83,"passed_time":33.85548258,"remaining_time":87.0569552},
{"learn":[0.2489204755],"iteration":84,"passed_time":34.24750326,"remaining_time":86.62603765},
{"learn":[0.2481622652],"iteration":85,"passed_time":34.56133383,"remaining_time":86.0014586},
{"learn":[0.2475076373],"iteration":86,"passed_time":35.02186373,"remaining_time":85.74318361},
{"learn":[0.2468310658],"iteration":87,"passed_time":35.38381005,"remaining_time":85.24281511},
{"learn":[0.2464072204],"iteration":88,"passed_time":35.75564775,"remaining_time":84.7690076},
{"learn":[0.2459487588],"iteration":89,"passed_time":36.02867189,"remaining_time":84.06690108},
{"learn":[0.2454207635],"iteration":90,"passed_time":36.34514595,"remaining_time":83.47401653},
{"learn":[0.2449452037],"iteration":91,"passed_time":36.67714008,"remaining_time":82.92222975},
{"learn":[0.2442793013],"iteration":92,"passed_time":37.06972271,"remaining_time":82.51002796},
{"learn":[0.2438298983],"iteration":93,"passed_time":37.41831284,"remaining_time":82.00183451},
{"learn":[0.2434671738],"iteration":94,"passed_time":37.70717866,"remaining_time":81.36812237},
{"learn":[0.2428874248],"iteration":95,"passed_time":38.30897519,"remaining_time":81.40657229},
{"learn":[0.242248933],"iteration":96,"passed_time":38.68680357,"remaining_time":80.96310438},
{"learn":[0.2416022874],"iteration":97,"passed_time":39.17264563,"remaining_time":80.7436165},
{"learn":[0.24103164],"iteration":98,"passed_time":40.05765418,"remaining_time":81.32917668},
{"learn":[0.2399505511],"iteration":99,"passed_time":40.62468979,"remaining_time":81.24937958},
{"learn":[0.2393780192],"iteration":100,"passed_time":41.04277545,"remaining_time":80.86645856},
{"learn":[0.2391310121],"iteration":101,"passed_time":41.49434015,"remaining_time":80.54783676},
{"learn":[0.2387754516],"iteration":102,"passed_time":41.82303318,"remaining_time":79.99162656},
{"learn":[0.2383011856],"iteration":103,"passed_time":42.18097266,"remaining_time":79.49491001},
{"learn":[0.2379647947],"iteration":104,"passed_time":42.49700477,"remaining_time":78.92300886},
{"learn":[0.2374954977],"iteration":105,"passed_time":42.85199615,"remaining_time":78.42723823},
{"learn":[0.2371353675],"iteration":106,"passed_time":43.19496968,"remaining_time":77.91242195},
{"learn":[0.2365183494],"iteration":107,"passed_time":43.65163128,"remaining_time":77.60290005},
{"learn":[0.2361467469],"iteration":108,"passed_time":43.98850252,"remaining_time":77.08077047},
{"learn":[0.2358130979],"iteration":109,"passed_time":44.26915067,"remaining_time":76.46489661},
{"learn":[0.2353517859],"iteration":110,"passed_time":44.73352245,"remaining_time":76.16788957},
{"learn":[0.2349656534],"iteration":111,"passed_time":45.53218297,"remaining_time":76.42902142},
{"learn":[0.234605414],"iteration":112,"passed_time":45.8955586,"remaining_time":75.95105715},
{"learn":[0.2342336359],"iteration":113,"passed_time":46.58961642,"remaining_time":76.01463732},
{"learn":[0.2336228904],"iteration":114,"passed_time":46.95312459,"remaining_time":75.53328738},
{"learn":[0.2333606402],"iteration":115,"passed_time":47.32770999,"remaining_time":75.07153998},
{"learn":[0.2330786154],"iteration":116,"passed_time":47.69084699,"remaining_time":74.59337607},
{"learn":[0.2328506377],"iteration":117,"passed_time":48.16617368,"remaining_time":74.29020008},
{"learn":[0.232531202],"iteration":118,"passed_time":48.40071221,"remaining_time":73.61789},
{"learn":[0.232275125],"iteration":119,"passed_time":48.74358458,"remaining_time":73.11537686},
{"learn":[0.2318666932],"iteration":120,"passed_time":49.07152233,"remaining_time":72.59340906},
{"learn":[0.2316018588],"iteration":121,"passed_time":49.38580951,"remaining_time":72.05470568},
{"learn":[0.2313077279],"iteration":122,"passed_time":49.75559255,"remaining_time":71.59951124},
{"learn":[0.2309067006],"iteration":123,"passed_time":50.42190797,"remaining_time":71.56657905},
{"learn":[0.2306447955],"iteration":124,"passed_time":51.1051123,"remaining_time":71.54715722},
{"learn":[0.2302184505],"iteration":125,"passed_time":51.50269758,"remaining_time":71.12277284},
{"learn":[0.230016713],"iteration":126,"passed_time":52.03157848,"remaining_time":70.87766203},
{"learn":[0.229632457],"iteration":127,"passed_time":52.32899422,"remaining_time":70.31708598},
{"learn":[0.2293053209],"iteration":128,"passed_time":52.65630419,"remaining_time":69.80021718},
{"learn":[0.2288395568],"iteration":129,"passed_time":53.14083311,"remaining_time":69.49185868},
{"learn":[0.2285842158],"iteration":130,"passed_time":53.51481052,"remaining_time":69.03819067},
{"learn":[0.2282376538],"iteration":131,"passed_time":53.86459133,"remaining_time":68.55493443},
{"learn":[0.2280575324],"iteration":132,"passed_time":54.11460835,"remaining_time":67.948418},
{"learn":[0.2275275147],"iteration":133,"passed_time":54.49575895,"remaining_time":67.50967154},
{"learn":[0.2272616819],"iteration":134,"passed_time":54.90723508,"remaining_time":67.10884287},
{"learn":[0.2269895102],"iteration":135,"passed_time":55.27550756,"remaining_time":66.65575912},
{"learn":[0.2266328201],"iteration":136,"passed_time":55.59004004,"remaining_time":66.13997464},
{"learn":[0.2263737514],"iteration":137,"passed_time":55.94823464,"remaining_time":65.67836241},
{"learn":[0.2260415648],"iteration":138,"passed_time":56.31715245,"remaining_time":65.23065859},
{"learn":[0.2255217558],"iteration":139,"passed_time":56.74880863,"remaining_time":64.85578129},
{"learn":[0.2252476196],"iteration":140,"passed_time":57.04707831,"remaining_time":64.32968405},
{"learn":[0.224996088],"iteration":141,"passed_time":57.37893802,"remaining_time":63.84417047},
{"learn":[0.2246658962],"iteration":142,"passed_time":57.7049341,"remaining_time":63.35436821},
{"learn":[0.2242980944],"iteration":143,"passed_time":58.07547229,"remaining_time":62.91509498},
{"learn":[0.2240711909],"iteration":144,"passed_time":58.47659391,"remaining_time":62.50946246},
{"learn":[0.2237288177],"iteration":145,"passed_time":58.87127166,"remaining_time":62.09709477},
{"learn":[0.2234802235],"iteration":146,"passed_time":59.1725627,"remaining_time":61.58776934},
{"learn":[0.2232521596],"iteration":147,"passed_time":59.46939819,"remaining_time":61.07667922},
{"learn":[0.2230617206],"iteration":148,"passed_time":59.74731577,"remaining_time":60.54929316},
{"learn":[0.2228335775],"iteration":149,"passed_time":60.00885643,"remaining_time":60.00885643},
{"learn":[0.2225731252],"iteration":150,"passed_time":60.50211755,"remaining_time":59.700765},
{"learn":[0.2223055478],"iteration":151,"passed_time":60.82709569,"remaining_time":59.22638265},
{"learn":[0.2220463319],"iteration":152,"passed_time":61.14985783,"remaining_time":58.75182419},
{"learn":[0.2217492484],"iteration":153,"passed_time":61.54437005,"remaining_time":58.34725991},
{"learn":[0.2214913912],"iteration":154,"passed_time":61.93366728,"remaining_time":57.93794681},
{"learn":[0.2212670422],"iteration":155,"passed_time":62.23205929,"remaining_time":57.4449778},
{"learn":[0.2210331231],"iteration":156,"passed_time":62.5211891,"remaining_time":56.94605122},
{"learn":[0.2207465594],"iteration":157,"passed_time":62.87095192,"remaining_time":56.50427324},
{"learn":[0.220527731],"iteration":158,"passed_time":63.36644512,"remaining_time":56.19288529},
{"learn":[0.2202922715],"iteration":159,"passed_time":63.59091105,"remaining_time":55.64204717},
{"learn":[0.2200593577],"iteration":160,"passed_time":63.85823772,"remaining_time":55.13226735},
{"learn":[0.2195536744],"iteration":161,"passed_time":64.14796698,"remaining_time":54.64456447},
{"learn":[0.2194048515],"iteration":162,"passed_time":64.45820142,"remaining_time":54.17652512},
{"learn":[0.2192004322],"iteration":163,"passed_time":64.64655408,"remaining_time":53.60933753},
{"learn":[0.2189039015],"iteration":164,"passed_time":65.06108139,"remaining_time":53.23179387},
{"learn":[0.2182837433],"iteration":165,"passed_time":65.3670095,"remaining_time":52.7661402},
{"learn":[0.2180844148],"iteration":166,"passed_time":65.63192021,"remaining_time":52.26973286},
{"learn":[0.2178033904],"iteration":167,"passed_time":65.91937085,"remaining_time":51.79379139},
{"learn":[0.2175854072],"iteration":168,"passed_time":66.19049832,"remaining_time":51.30742769},
{"learn":[0.2173690565],"iteration":169,"passed_time":66.50671572,"remaining_time":50.85807673},
{"learn":[0.21715024],"iteration":170,"passed_time":66.82104832,"remaining_time":50.40886102},
{"learn":[0.2169008501],"iteration":171,"passed_time":67.14144223,"remaining_time":49.96572445},
{"learn":[0.2166579587],"iteration":172,"passed_time":67.39494854,"remaining_time":49.47490442},
{"learn":[0.2165541393],"iteration":173,"passed_time":67.62166985,"remaining_time":48.9674161},
{"learn":[0.2163503883],"iteration":174,"passed_time":67.87450443,"remaining_time":48.48178888},
{"learn":[0.2161764649],"iteration":175,"passed_time":68.08837042,"remaining_time":47.97135189},
{"learn":[0.2159845033],"iteration":176,"passed_time":68.32585289,"remaining_time":47.48067743},
{"learn":[0.2157138814],"iteration":177,"passed_time":68.58307784,"remaining_time":47.00637919},
{"learn":[0.215476544],"iteration":178,"passed_time":68.81210602,"remaining_time":46.51544597},
{"learn":[0.2152475603],"iteration":179,"passed_time":69.07854162,"remaining_time":46.05236108},
{"learn":[0.2149566177],"iteration":180,"passed_time":69.3063195,"remaining_time":45.56603326},
{"learn":[0.2147408568],"iteration":181,"passed_time":69.52094813,"remaining_time":45.07402132},
{"learn":[0.2145190552],"iteration":182,"passed_time":69.81140621,"remaining_time":44.633522},
{"learn":[0.2143532328],"iteration":183,"passed_time":70.05264927,"remaining_time":44.16362672},
{"learn":[0.2141601188],"iteration":184,"passed_time":70.27289671,"remaining_time":43.68315201},
{"learn":[0.2140060828],"iteration":185,"passed_time":70.50184577,"remaining_time":43.2108087},
{"learn":[0.2138565062],"iteration":186,"passed_time":70.70467264,"remaining_time":42.72528347},
{"learn":[0.2137075788],"iteration":187,"passed_time":70.88410231,"remaining_time":42.22882691},
{"learn":[0.2135431437],"iteration":188,"passed_time":71.07926571,"remaining_time":41.74496558},
{"learn":[0.2132958429],"iteration":189,"passed_time":71.27772809,"remaining_time":41.2660531},
{"learn":[0.2131386713],"iteration":190,"passed_time":71.50640511,"remaining_time":40.80732019},
{"learn":[0.2129898509],"iteration":191,"passed_time":71.68936704,"remaining_time":40.32526896},
{"learn":[0.2127951234],"iteration":192,"passed_time":71.86571631,"remaining_time":39.84265101},
{"learn":[0.2126025232],"iteration":193,"passed_time":72.08211696,"remaining_time":39.38507421},
{"learn":[0.2124503908],"iteration":194,"passed_time":72.30125058,"remaining_time":38.93144262},
{"learn":[0.2123293983],"iteration":195,"passed_time":72.55129097,"remaining_time":38.49660337},
{"learn":[0.2121860933],"iteration":196,"passed_time":72.78108772,"remaining_time":38.05305602},
{"learn":[0.2120405042],"iteration":197,"passed_time":73.01280989,"remaining_time":37.61265964},
{"learn":[0.2118403475],"iteration":198,"passed_time":73.17144243,"remaining_time":37.13726475},
{"learn":[0.2116795742],"iteration":199,"passed_time":73.40156688,"remaining_time":36.70078344},
{"learn":[0.211508992],"iteration":200,"passed_time":73.64267762,"remaining_time":36.27176659},
{"learn":[0.2113128367],"iteration":201,"passed_time":73.86828053,"remaining_time":35.83708659},
{"learn":[0.2110726417],"iteration":202,"passed_time":74.08620627,"remaining_time":35.40079807},
{"learn":[0.2109134784],"iteration":203,"passed_time":74.33087843,"remaining_time":34.97923691},
{"learn":[0.2107593174],"iteration":204,"passed_time":74.58154959,"remaining_time":34.56218152},
{"learn":[0.2105833075],"iteration":205,"passed_time":74.76392325,"remaining_time":34.11557663},
{"learn":[0.2104433533],"iteration":206,"passed_time":74.94393399,"remaining_time":33.6704631},
{"learn":[0.2103210524],"iteration":207,"passed_time":75.16985053,"remaining_time":33.24820312},
{"learn":[0.2101571062],"iteration":208,"passed_time":75.31988449,"remaining_time":32.79478224},
{"learn":[0.2099957922],"iteration":209,"passed_time":75.58365973,"remaining_time":32.39299703},
{"learn":[0.2098143544],"iteration":210,"passed_time":75.74228998,"remaining_time":31.94816971},
{"learn":[0.2096035138],"iteration":211,"passed_time":75.86266754,"remaining_time":31.49016388},
{"learn":[0.2091203394],"iteration":212,"passed_time":76.05354777,"remaining_time":31.06412515},
{"learn":[0.2089907382],"iteration":213,"passed_time":76.18667949,"remaining_time":30.6170768},
{"learn":[0.2088291334],"iteration":214,"passed_time":76.31793733,"remaining_time":30.17220778},
{"learn":[0.2085834186],"iteration":215,"passed_time":76.47665829,"remaining_time":29.74092267},
{"learn":[0.2084212562],"iteration":216,"passed_time":76.62754099,"remaining_time":29.30915162},
{"learn":[0.2082770149],"iteration":217,"passed_time":76.78104605,"remaining_time":28.88094393},
{"learn":[0.2081249686],"iteration":218,"passed_time":76.97229644,"remaining_time":28.46920553},
{"learn":[0.2080224914],"iteration":219,"passed_time":77.08428329,"remaining_time":28.03064847},
{"learn":[0.2079078315],"iteration":220,"passed_time":77.26738339,"remaining_time":27.62046737},
{"learn":[0.207719278],"iteration":221,"passed_time":77.40569388,"remaining_time":27.19659515},
{"learn":[0.2074512916],"iteration":222,"passed_time":77.59398421,"remaining_time":26.79254163},
{"learn":[0.2073311512],"iteration":223,"passed_time":77.7369179,"remaining_time":26.37502572},
{"learn":[0.2071911302],"iteration":224,"passed_time":77.86153508,"remaining_time":25.95384503},
{"learn":[0.2071250893],"iteration":225,"passed_time":77.98387551,"remaining_time":25.53454331},
{"learn":[0.206939855],"iteration":226,"passed_time":78.11734577,"remaining_time":25.12143719},
{"learn":[0.206804801],"iteration":227,"passed_time":78.29413745,"remaining_time":24.72446446},
{"learn":[0.2066712457],"iteration":228,"passed_time":78.48350417,"remaining_time":24.33331352},
{"learn":[0.206538836],"iteration":229,"passed_time":78.65558766,"remaining_time":23.93865711},
{"learn":[0.2063751938],"iteration":230,"passed_time":78.80589795,"remaining_time":23.53942406},
{"learn":[0.2062618022],"iteration":231,"passed_time":78.97546507,"remaining_time":23.14798114},
{"learn":[0.2061444762],"iteration":232,"passed_time":79.10377392,"remaining_time":22.74657877},
{"learn":[0.2059814308],"iteration":233,"passed_time":79.2451171,"remaining_time":22.35118688},
{"learn":[0.2058757611],"iteration":234,"passed_time":79.39035391,"remaining_time":21.95903406},
{"learn":[0.2057608634],"iteration":235,"passed_time":79.55772712,"remaining_time":21.57497685},
{"learn":[0.2056572975],"iteration":236,"passed_time":79.69909001,"remaining_time":21.18583405},
{"learn":[0.2054647381],"iteration":237,"passed_time":79.85473348,"remaining_time":20.8024936},
{"learn":[0.2053433827],"iteration":238,"passed_time":80.00527373,"remaining_time":20.41975606},
{"learn":[0.2052075377],"iteration":239,"passed_time":80.12517363,"remaining_time":20.03129341},
{"learn":[0.2049936188],"iteration":240,"passed_time":80.29018467,"remaining_time":19.6561033},
{"learn":[0.2048433667],"iteration":241,"passed_time":80.43034442,"remaining_time":19.27669412},
{"learn":[0.2047026629],"iteration":242,"passed_time":80.57944319,"remaining_time":18.90135087},
{"learn":[0.2045246111],"iteration":243,"passed_time":80.76238454,"remaining_time":18.53562924},
{"learn":[0.2044036362],"iteration":244,"passed_time":80.90667037,"remaining_time":18.16272192},
{"learn":[0.2042745873],"iteration":245,"passed_time":81.02744096,"remaining_time":17.78651143},
{"learn":[0.204089517],"iteration":246,"passed_time":81.19808164,"remaining_time":17.42307015},
{"learn":[0.2039461581],"iteration":247,"passed_time":81.36930414,"remaining_time":17.06130571},
{"learn":[0.2038300429],"iteration":248,"passed_time":81.50650287,"remaining_time":16.694103},
{"learn":[0.2036769],"iteration":249,"passed_time":81.65887724,"remaining_time":16.33177545},
{"learn":[0.2035191769],"iteration":250,"passed_time":81.75094145,"remaining_time":15.95934714},
{"learn":[0.2034058845],"iteration":251,"passed_time":81.87217395,"remaining_time":15.5946998},
{"learn":[0.2032739449],"iteration":252,"passed_time":81.93986418,"remaining_time":15.2220301},
{"learn":[0.2031946757],"iteration":253,"passed_time":82.04098166,"remaining_time":14.85781558},
{"learn":[0.2031260926],"iteration":254,"passed_time":82.11323405,"remaining_time":14.49057072},
{"learn":[0.2030254435],"iteration":255,"passed_time":82.19015498,"remaining_time":14.12643289},
{"learn":[0.2028296793],"iteration":256,"passed_time":82.27124144,"remaining_time":13.76522717},
{"learn":[0.2027450856],"iteration":257,"passed_time":82.34173454,"remaining_time":13.40446841},
{"learn":[0.2025843864],"iteration":258,"passed_time":82.43187353,"remaining_time":13.04906106},
{"learn":[0.2024918489],"iteration":259,"passed_time":82.54784968,"remaining_time":12.69966918},
{"learn":[0.2023705127],"iteration":260,"passed_time":82.62047698,"remaining_time":12.34558851},
{"learn":[0.2021339539],"iteration":261,"passed_time":82.73356926,"remaining_time":11.99952531},
{"learn":[0.2020166988],"iteration":262,"passed_time":82.86275489,"remaining_time":11.65749784},
{"learn":[0.2018815866],"iteration":263,"passed_time":82.94057017,"remaining_time":11.31007775},
{"learn":[0.2017344458],"iteration":264,"passed_time":83.01746747,"remaining_time":10.96457118},
{"learn":[0.2015746288],"iteration":265,"passed_time":83.10212849,"remaining_time":10.62207657},
{"learn":[0.2014361107],"iteration":266,"passed_time":83.21491541,"remaining_time":10.28498955},
{"learn":[0.2013300759],"iteration":267,"passed_time":83.28503176,"remaining_time":9.944481404},
{"learn":[0.201242011],"iteration":268,"passed_time":83.42466285,"remaining_time":9.613994604},
{"learn":[0.2011333044],"iteration":269,"passed_time":83.49130577,"remaining_time":9.276811752},
{"learn":[0.2009961638],"iteration":270,"passed_time":83.55944733,"remaining_time":8.941785876},
{"learn":[0.2009105254],"iteration":271,"passed_time":83.63902495,"remaining_time":8.609899627},
{"learn":[0.2008062037],"iteration":272,"passed_time":83.70911584,"remaining_time":8.278923545},
{"learn":[0.2007465901],"iteration":273,"passed_time":83.79822394,"remaining_time":7.951656286},
{"learn":[0.2006036688],"iteration":274,"passed_time":83.90733535,"remaining_time":7.627939577},
{"learn":[0.2005092294],"iteration":275,"passed_time":84.01235334,"remaining_time":7.305422029},
{"learn":[0.2004134971],"iteration":276,"passed_time":84.09305377,"remaining_time":6.982455728},
{"learn":[0.2003019137],"iteration":277,"passed_time":84.21235672,"remaining_time":6.664287222},
{"learn":[0.200134577],"iteration":278,"passed_time":84.29595959,"remaining_time":6.344857174},
{"learn":[0.2000541561],"iteration":279,"passed_time":84.3702307,"remaining_time":6.02644505},
{"learn":[0.1999042352],"iteration":280,"passed_time":84.45993653,"remaining_time":5.710814214},
{"learn":[0.1997773934],"iteration":281,"passed_time":84.55775108,"remaining_time":5.39730326},
{"learn":[0.1996709591],"iteration":282,"passed_time":84.62369643,"remaining_time":5.083402259},
{"learn":[0.1994638197],"iteration":283,"passed_time":84.70614666,"remaining_time":4.772177277},
{"learn":[0.1993737659],"iteration":284,"passed_time":84.78696188,"remaining_time":4.462471678},
{"learn":[0.1992846096],"iteration":285,"passed_time":84.86294741,"remaining_time":4.154130293},
{"learn":[0.1991687051],"iteration":286,"passed_time":84.93892593,"remaining_time":3.847407795},
{"learn":[0.1990268572],"iteration":287,"passed_time":85.02214711,"remaining_time":3.542589463},
{"learn":[0.1989285535],"iteration":288,"passed_time":85.09976148,"remaining_time":3.239091267},
{"learn":[0.1988359651],"iteration":289,"passed_time":85.16896151,"remaining_time":2.936860742},
{"learn":[0.1987094433],"iteration":290,"passed_time":85.25205444,"remaining_time":2.636661477},
{"learn":[0.1985628222],"iteration":291,"passed_time":85.33277691,"remaining_time":2.337884299},
{"learn":[0.1984121857],"iteration":292,"passed_time":85.4340606,"remaining_time":2.041086772},
{"learn":[0.1983221191],"iteration":293,"passed_time":85.50258694,"remaining_time":1.744950754},
{"learn":[0.1982331663],"iteration":294,"passed_time":85.5887881,"remaining_time":1.450657425},
{"learn":[0.1980863067],"iteration":295,"passed_time":85.67002743,"remaining_time":1.157703073},
{"learn":[0.1979827111],"iteration":296,"passed_time":85.760733,"remaining_time":0.8662700303},
{"learn":[0.1978773627],"iteration":297,"passed_time":85.8179384,"remaining_time":0.5759593181},
{"learn":[0.1977784013],"iteration":298,"passed_time":85.91371028,"remaining_time":0.2873368237},
{"learn":[0.1976528158],"iteration":299,"passed_time":85.98873937,"remaining_time":0}
]}ng_time":0}
]}